video_dataloader_pytorch/__init__.py
video_dataloader_pytorch/base/__init__.py
video_dataloader_pytorch/base/base_data_loader.py
video_dataloader_pytorch/base/base_model.py
video_dataloader_pytorch/data_loader/__init__.py
video_dataloader_pytorch/data_loader/data_loaders.py
video_dataloader_pytorch/data_loader/dataset.py
video_dataloader_pytorch/data_loader/transforms.py
video_dataloader_pytorch/utils/__init__.py
video_dataloader_pytorch/utils/data.py
video_dataloader_pytorch/utils/sampler.py
video_dataloader_pytorch/utils/util.py
video_dataloader_for_pytorch-0.1.post1.dist-info/METADATA
video_dataloader_for_pytorch-0.1.post1.dist-info/WHEEL
video_dataloader_for_pytorch-0.1.post1.dist-info/top_level.txt
video_dataloader_for_pytorch-0.1.post1.dist-info/RECORD
